diagrams_ext/__init__.py
diagrams_ext/alibabacloud/__init__.py
diagrams_ext/alibabacloud/analytics.py
diagrams_ext/alibabacloud/application.py
diagrams_ext/alibabacloud/communication.py
diagrams_ext/alibabacloud/compute.py
diagrams_ext/alibabacloud/database.py
diagrams_ext/alibabacloud/iot.py
diagrams_ext/alibabacloud/network.py
diagrams_ext/alibabacloud/security.py
diagrams_ext/alibabacloud/storage.py
diagrams_ext/alibabacloud/web.py
diagrams_ext/aws/__init__.py
diagrams_ext/aws/analytics.py
diagrams_ext/aws/ar.py
diagrams_ext/aws/blockchain.py
diagrams_ext/aws/business.py
diagrams_ext/aws/compute.py
diagrams_ext/aws/cost.py
diagrams_ext/aws/database.py
diagrams_ext/aws/devtools.py
diagrams_ext/aws/enablement.py
diagrams_ext/aws/enduser.py
diagrams_ext/aws/engagement.py
diagrams_ext/aws/game.py
diagrams_ext/aws/general.py
diagrams_ext/aws/integration.py
diagrams_ext/aws/iot.py
diagrams_ext/aws/management.py
diagrams_ext/aws/media.py
diagrams_ext/aws/migration.py
diagrams_ext/aws/ml.py
diagrams_ext/aws/mobile.py
diagrams_ext/aws/network.py
diagrams_ext/aws/quantum.py
diagrams_ext/aws/robotics.py
diagrams_ext/aws/satellite.py
diagrams_ext/aws/security.py
diagrams_ext/aws/storage.py
diagrams_ext/azure/__init__.py
diagrams_ext/azure/analytics.py
diagrams_ext/azure/compute.py
diagrams_ext/azure/database.py
diagrams_ext/azure/devops.py
diagrams_ext/azure/general.py
diagrams_ext/azure/identity.py
diagrams_ext/azure/integration.py
diagrams_ext/azure/iot.py
diagrams_ext/azure/migration.py
diagrams_ext/azure/ml.py
diagrams_ext/azure/mobile.py
diagrams_ext/azure/network.py
diagrams_ext/azure/security.py
diagrams_ext/azure/storage.py
diagrams_ext/azure/web.py
diagrams_ext/base/__init__.py
diagrams_ext/c4/__init__.py
diagrams_ext/custom/__init__.py
diagrams_ext/digitalocean/__init__.py
diagrams_ext/digitalocean/compute.py
diagrams_ext/digitalocean/database.py
diagrams_ext/digitalocean/network.py
diagrams_ext/digitalocean/storage.py
diagrams_ext/elastic/__init__.py
diagrams_ext-0.23.5a7.dist-info/LICENSE
diagrams_ext-0.23.5a7.dist-info/METADATA
diagrams_ext-0.23.5a7.dist-info/WHEEL
diagrams_ext-0.23.5a7.dist-info/RECORD
