Metadata-Version: 2.1
Name: diagrams_ext
Version: 0.23.5a7
Summary: Diagram as Code
Home-page: https://diagrams.mingrammer.com
License: MIT
Author: Anddd7
Author-email: anddd7@icloud.com
Requires-Python: >=3.7,<4.0
Classifier: License :: OSI Approved :: MIT License
Classifier: Programming Language :: Python :: 3
Classifier: Programming Language :: Python :: 3.7
Classifier: Programming Language :: Python :: 3.8
Classifier: Programming Language :: Python :: 3.9
Classifier: Programming Language :: Python :: 3.10
Classifier: Programming Language :: Python :: 3.11
Classifier: Programming Language :: Python :: 3.12
Requires-Dist: graphviz (>=0.13.2,<0.21.0)
Requires-Dist: jinja2 (>=2.10,<4.0)
Requires-Dist: requests (>=2.31.0,<3.0.0)
Requires-Dist: typed-ast (>=1.5.4,<2.0.0)
Project-URL: Repository, https://github.com/Anddd7/diagrams
